anaton/__init__.py
anaton/dictionary.py
anaton/solver.py
anaton/utils.py
anaton/wordlist10000
AnaTon-1.1.2.dist-info/METADATA
AnaTon-1.1.2.dist-info/WHEEL
AnaTon-1.1.2.dist-info/top_level.txt
AnaTon-1.1.2.dist-info/RECORD
