Metadata-Version: 2.1
Name: AnaTon
Version: 1.1.2
Summary: Extremely fast anagram solver
Home-page: https://github.com/Odder/AnaTon
Author: Oscar Roth Andersen
Author-email: oscarrothandersen@gmail.com
License: MIT
Platform: UNKNOWN
Requires-Python: >=3.7
